{
  "title": "코스 요소 타입",
  "description": "5 minutes to learn the most important Docusaurus concepts.",
  "slug": "/category/코스-요소-타입-3",
  "permalink": "/docs/category/코스-요소-타입-3",
  "navigation": {
    "previous": {
      "title": "가상 교실",
      "permalink": "/docs/types-of-course-element/communication-and-organisation/virtual-classrooms"
    },
    "next": {
      "title": "과정 요소: card2brain Flashcards",
      "permalink": "/docs/types-of-course-element/knowledge-transfer/course-element-card2brain"
    }
  }
}