{
  "/__docusaurus/debug-fab": {
    "__comp": "__comp---theme-debug-config-23-a-2ff",
    "__context": {
      "plugin": "plugin---docusaurus-debugb-0-b-f5f"
    }
  },
  "/__docusaurus/debug/config-3f1": {
    "__comp": "__comp---theme-debug-config-23-a-2ff",
    "__context": {
      "plugin": "plugin---docusaurus-debugb-0-b-f5f"
    }
  },
  "/__docusaurus/debug/content-2d3": {
    "__comp": "__comp---theme-debug-contentba-8-ce7",
    "__context": {
      "plugin": "plugin---docusaurus-debugb-0-b-f5f"
    },
    "allContent": "allContent---docusaurus-debug-content-246-9aa"
  },
  "/__docusaurus/debug/globalData-41f": {
    "__comp": "__comp---theme-debug-global-dataede-0fa",
    "__context": {
      "plugin": "plugin---docusaurus-debugb-0-b-f5f"
    }
  },
  "/__docusaurus/debug/metadata-70b": {
    "__comp": "__comp---theme-debug-site-metadata-68-e-3d4",
    "__context": {
      "plugin": "plugin---docusaurus-debugb-0-b-f5f"
    }
  },
  "/__docusaurus/debug/registry-ed6": {
    "__comp": "__comp---theme-debug-registry-679-501",
    "__context": {
      "plugin": "plugin---docusaurus-debugb-0-b-f5f"
    }
  },
  "/__docusaurus/debug/routes-5bd": {
    "__comp": "__comp---theme-debug-routes-946-699",
    "__context": {
      "plugin": "plugin---docusaurus-debugb-0-b-f5f"
    }
  },
  "/blog-c4e": {
    "__comp": "__comp---theme-blog-list-pagea-6-a-7ba",
    "__context": {
      "plugin": "plugin---blog-749-0f3"
    },
    "sidebar": "sidebar---blog-814-8ac",
    "items": [
      {
        "content": "content---blog-766-e3c"
      },
      {
        "content": "content---blogf-4-f-cd7"
      },
      {
        "content": "content---blog-871-381"
      },
      {
        "content": "content---blog-925-e00"
      }
    ],
    "metadata": "metadata---blogb-2-b-df1"
  },
  "/blog/archive-68f": {
    "__comp": "__comp---theme-blog-archive-page-9-e-4-1d8",
    "__context": {
      "plugin": "plugin---blog-749-0f3"
    },
    "archive": "archive---blog-archiveb-2-f-393"
  },
  "/blog/first-blog-post-06b": {
    "__comp": "__comp---theme-blog-post-pageccc-cab",
    "__context": {
      "plugin": "plugin---blog-749-0f3"
    },
    "sidebar": "sidebar---blog-814-8ac",
    "content": "content---blog-first-blog-poste-27-4a1"
  },
  "/blog/long-blog-post-efe": {
    "__comp": "__comp---theme-blog-post-pageccc-cab",
    "__context": {
      "plugin": "plugin---blog-749-0f3"
    },
    "sidebar": "sidebar---blog-814-8ac",
    "content": "content---blog-long-blog-post-736-bc7"
  },
  "/blog/mdx-blog-post-ba8": {
    "__comp": "__comp---theme-blog-post-pageccc-cab",
    "__context": {
      "plugin": "plugin---blog-749-0f3"
    },
    "sidebar": "sidebar---blog-814-8ac",
    "content": "content---blog-mdx-blog-post-593-37b"
  },
  "/blog/tags-2e7": {
    "__comp": "__comp---theme-blog-tags-list-page-01-a-d0b",
    "__context": {
      "plugin": "plugin---blog-749-0f3"
    },
    "sidebar": "sidebar---blog-814-8ac",
    "tags": "tags---blog-tagsa-70-da2"
  },
  "/blog/tags/docusaurus-6fb": {
    "__comp": "__comp---theme-blog-tags-posts-page-687-b6c",
    "__context": {
      "plugin": "plugin---blog-749-0f3"
    },
    "sidebar": "sidebar---blog-814-8ac",
    "items": [
      {
        "content": "content---blog-766-e3c"
      },
      {
        "content": "content---blogf-4-f-cd7"
      },
      {
        "content": "content---blog-871-381"
      },
      {
        "content": "content---blog-925-e00"
      }
    ],
    "tag": "tag---blog-tags-docusaurusa-80-728",
    "listMetadata": "listMetadata---blog-tags-docusaurus-608-c09"
  },
  "/blog/tags/facebook-ebb": {
    "__comp": "__comp---theme-blog-tags-posts-page-687-b6c",
    "__context": {
      "plugin": "plugin---blog-749-0f3"
    },
    "sidebar": "sidebar---blog-814-8ac",
    "items": [
      {
        "content": "content---blog-766-e3c"
      }
    ],
    "tag": "tag---blog-tags-facebook-031-c52",
    "listMetadata": "listMetadata---blog-tags-facebook-096-d31"
  },
  "/blog/tags/hello-0cb": {
    "__comp": "__comp---theme-blog-tags-posts-page-687-b6c",
    "__context": {
      "plugin": "plugin---blog-749-0f3"
    },
    "sidebar": "sidebar---blog-814-8ac",
    "items": [
      {
        "content": "content---blog-766-e3c"
      },
      {
        "content": "content---blog-871-381"
      }
    ],
    "tag": "tag---blog-tags-hello-30-a-bed",
    "listMetadata": "listMetadata---blog-tags-hello-664-70a"
  },
  "/blog/tags/hola-425": {
    "__comp": "__comp---theme-blog-tags-posts-page-687-b6c",
    "__context": {
      "plugin": "plugin---blog-749-0f3"
    },
    "sidebar": "sidebar---blog-814-8ac",
    "items": [
      {
        "content": "content---blog-925-e00"
      }
    ],
    "tag": "tag---blog-tags-holae-16-18a",
    "listMetadata": "listMetadata---blog-tags-hola-4-c-9-a24"
  },
  "/blog/welcome-6c2": {
    "__comp": "__comp---theme-blog-post-pageccc-cab",
    "__context": {
      "plugin": "plugin---blog-749-0f3"
    },
    "sidebar": "sidebar---blog-814-8ac",
    "content": "content---blog-welcomed-9-f-ffb"
  },
  "/markdown-page-924": {
    "__comp": "__comp---theme-mdx-page-1-f-3-b90",
    "__context": {
      "plugin": "plugin---markdown-pageb-09-bff"
    },
    "content": "content---markdown-page-393-028"
  },
  "/docs-7fc": {
    "__comp": "__comp---theme-doc-page-1-be-9be",
    "__context": {
      "plugin": "plugin---docs-447-111"
    },
    "versionMetadata": "versionMetadata---docs-935-398"
  },
  "/docs/authoring/actions-in-the-authoring-section-fe8": {
    "__comp": "__comp---theme-doc-item-178-a40",
    "content": "content---docs-authoring-actions-in-the-authoring-sectionf-54-4ac"
  },
  "/docs/authoring/detailed-view-od-learning-resources-a40": {
    "__comp": "__comp---theme-doc-item-178-a40",
    "content": "content---docs-authoring-detailed-view-od-learning-resources-583-f9f"
  },
  "/docs/authoring/set-up-info-page-fa4": {
    "__comp": "__comp---theme-doc-item-178-a40",
    "content": "content---docs-authoring-set-up-info-page-1-ef-db3"
  },
  "/docs/authoring/technical-information-on-resources-and-usage-c52": {
    "__comp": "__comp---theme-doc-item-178-a40",
    "content": "content---docs-authoring-technical-information-on-resources-and-usage-8-dc-a5e"
  },
  "/docs/authoring/various-types-of-learning-resources-7cd": {
    "__comp": "__comp---theme-doc-item-178-a40",
    "content": "content---docs-authoring-various-types-of-learning-resources-601-3ca"
  },
  "/docs/category/강의와-결석-9ed": {
    "__comp": "__comp---theme-doc-category-generated-index-page-14-e-640",
    "categoryGeneratedIndex": "categoryGeneratedIndex---docs-category-강의와-결석-467-943"
  },
  "/docs/category/개인메뉴-a67": {
    "__comp": "__comp---theme-doc-category-generated-index-page-14-e-640",
    "categoryGeneratedIndex": "categoryGeneratedIndex---docs-category-개인메뉴-667-075"
  },
  "/docs/category/개인메뉴-및-컴포넌트-4d3": {
    "__comp": "__comp---theme-doc-category-generated-index-page-14-e-640",
    "categoryGeneratedIndex": "categoryGeneratedIndex---docs-category-개인메뉴-및-컴포넌트-2-bf-d13"
  },
  "/docs/category/과정-요소의-일반-구성-f98": {
    "__comp": "__comp---theme-doc-category-generated-index-page-14-e-640",
    "categoryGeneratedIndex": "categoryGeneratedIndex---docs-category-과정-요소의-일반-구성e-94-dd3"
  },
  "/docs/category/구성-cf0": {
    "__comp": "__comp---theme-doc-category-generated-index-page-14-e-640",
    "categoryGeneratedIndex": "categoryGeneratedIndex---docs-category-구성-697-c8b"
  },
  "/docs/category/그룹-8a7": {
    "__comp": "__comp---theme-doc-category-generated-index-page-14-e-640",
    "categoryGeneratedIndex": "categoryGeneratedIndex---docs-category-그룹f-32-d57"
  },
  "/docs/category/기술-지원-da7": {
    "__comp": "__comp---theme-doc-category-generated-index-page-14-e-640",
    "categoryGeneratedIndex": "categoryGeneratedIndex---docs-category-기술-지원-73-f-02d"
  },
  "/docs/category/로그인-및-로그아웃-291": {
    "__comp": "__comp---theme-doc-category-generated-index-page-14-e-640",
    "categoryGeneratedIndex": "categoryGeneratedIndex---docs-category-로그인-및-로그아웃cb-3-3c9"
  },
  "/docs/category/문제-은행-8bc": {
    "__comp": "__comp---theme-doc-category-generated-index-page-14-e-640",
    "categoryGeneratedIndex": "categoryGeneratedIndex---docs-category-문제-은행-780-01c"
  },
  "/docs/category/블로그-제작-bef": {
    "__comp": "__comp---theme-doc-category-generated-index-page-14-e-640",
    "categoryGeneratedIndex": "categoryGeneratedIndex---docs-category-블로그-제작f-2-a-b0c"
  },
  "/docs/category/비디오-제작-ff2": {
    "__comp": "__comp---theme-doc-category-generated-index-page-14-e-640",
    "categoryGeneratedIndex": "categoryGeneratedIndex---docs-category-비디오-제작-8-e-0-21c"
  },
  "/docs/category/소개-c02": {
    "__comp": "__comp---theme-doc-category-generated-index-page-14-e-640",
    "categoryGeneratedIndex": "categoryGeneratedIndex---docs-category-소개-98-e-d4e"
  },
  "/docs/category/시험-에디터-qti-21-d6d": {
    "__comp": "__comp---theme-doc-category-generated-index-page-14-e-640",
    "categoryGeneratedIndex": "categoryGeneratedIndex---docs-category-시험-에디터-qti-21-e-20-357"
  },
  "/docs/category/위키-제작-731": {
    "__comp": "__comp---theme-doc-category-generated-index-page-14-e-640",
    "categoryGeneratedIndex": "categoryGeneratedIndex---docs-category-위키-제작-45-a-7f0"
  },
  "/docs/category/저작-9e1": {
    "__comp": "__comp---theme-doc-category-generated-index-page-14-e-640",
    "categoryGeneratedIndex": "categoryGeneratedIndex---docs-category-저작-0-cd-39c"
  },
  "/docs/category/전자-평가-d3d": {
    "__comp": "__comp---theme-doc-category-generated-index-page-14-e-640",
    "categoryGeneratedIndex": "categoryGeneratedIndex---docs-category-전자-평가-51-a-459"
  },
  "/docs/category/주제-할당-주제-관리-f41": {
    "__comp": "__comp---theme-doc-category-generated-index-page-14-e-640",
    "categoryGeneratedIndex": "categoryGeneratedIndex---docs-category-주제-할당-주제-관리-8-fa-b0e"
  },
  "/docs/category/지식-이전-a54": {
    "__comp": "__comp---theme-doc-category-generated-index-page-14-e-640",
    "categoryGeneratedIndex": "categoryGeneratedIndex---docs-category-지식-이전-8-b-9-62f"
  },
  "/docs/category/커리큘럼-관리-5b4": {
    "__comp": "__comp---theme-doc-category-generated-index-page-14-e-640",
    "categoryGeneratedIndex": "categoryGeneratedIndex---docs-category-커리큘럼-관리-4-f-8-a78"
  },
  "/docs/category/커뮤니케이션과-조직-0e2": {
    "__comp": "__comp---theme-doc-category-generated-index-page-14-e-640",
    "categoryGeneratedIndex": "categoryGeneratedIndex---docs-category-커뮤니케이션과-조직-4-df-95b"
  },
  "/docs/category/코스-내-폼-c9d": {
    "__comp": "__comp---theme-doc-category-generated-index-page-14-e-640",
    "categoryGeneratedIndex": "categoryGeneratedIndex---docs-category-코스-내-폼f-11-3fa"
  },
  "/docs/category/코스-내-학습활동-a73": {
    "__comp": "__comp---theme-doc-category-generated-index-page-14-e-640",
    "categoryGeneratedIndex": "categoryGeneratedIndex---docs-category-코스-내-학습활동b-3-e-8dc"
  },
  "/docs/category/코스-도구-사용-7eb": {
    "__comp": "__comp---theme-doc-category-generated-index-page-14-e-640",
    "categoryGeneratedIndex": "categoryGeneratedIndex---docs-category-코스-도구-사용b-29-dff"
  },
  "/docs/category/코스-설정-362": {
    "__comp": "__comp---theme-doc-category-generated-index-page-14-e-640",
    "categoryGeneratedIndex": "categoryGeneratedIndex---docs-category-코스-설정f-1-d-6f3"
  },
  "/docs/category/코스-요소-작업-179": {
    "__comp": "__comp---theme-doc-category-generated-index-page-14-e-640",
    "categoryGeneratedIndex": "categoryGeneratedIndex---docs-category-코스-요소-작업a-5-f-996"
  },
  "/docs/category/코스-요소-타입-278": {
    "__comp": "__comp---theme-doc-category-generated-index-page-14-e-640",
    "categoryGeneratedIndex": "categoryGeneratedIndex---docs-category-코스-요소-타입eae-09c"
  },
  "/docs/category/코스-운영-8b3": {
    "__comp": "__comp---theme-doc-category-generated-index-page-14-e-640",
    "categoryGeneratedIndex": "categoryGeneratedIndex---docs-category-코스-운영-42-c-671"
  },
  "/docs/category/코스-제작-b5d": {
    "__comp": "__comp---theme-doc-category-generated-index-page-14-e-640",
    "categoryGeneratedIndex": "categoryGeneratedIndex---docs-category-코스-제작-7-a-5-444"
  },
  "/docs/category/코스-제작-1-a97": {
    "__comp": "__comp---theme-doc-category-generated-index-page-14-e-640",
    "categoryGeneratedIndex": "categoryGeneratedIndex---docs-category-코스-제작-13-f-2-83a"
  },
  "/docs/category/코스와-카탈로그-c24": {
    "__comp": "__comp---theme-doc-category-generated-index-page-14-e-640",
    "categoryGeneratedIndex": "categoryGeneratedIndex---docs-category-코스와-카탈로그-7-e-7-b05"
  },
  "/docs/category/테스크-제작-391": {
    "__comp": "__comp---theme-doc-category-generated-index-page-14-e-640",
    "categoryGeneratedIndex": "categoryGeneratedIndex---docs-category-테스크-제작b-25-4f0"
  },
  "/docs/category/테스트-제작-ab7": {
    "__comp": "__comp---theme-doc-category-generated-index-page-14-e-640",
    "categoryGeneratedIndex": "categoryGeneratedIndex---docs-category-테스트-제작-1-f-4-9be"
  },
  "/docs/category/팟캐스트-제작-b0e": {
    "__comp": "__comp---theme-doc-category-generated-index-page-14-e-640",
    "categoryGeneratedIndex": "categoryGeneratedIndex---docs-category-팟캐스트-제작-7-e-1-456"
  },
  "/docs/category/평가-64a": {
    "__comp": "__comp---theme-doc-category-generated-index-page-14-e-640",
    "categoryGeneratedIndex": "categoryGeneratedIndex---docs-category-평가c-70-17f"
  },
  "/docs/category/평가-도구-e03": {
    "__comp": "__comp---theme-doc-category-generated-index-page-14-e-640",
    "categoryGeneratedIndex": "categoryGeneratedIndex---docs-category-평가-도구-9-b-6-09e"
  },
  "/docs/category/포트폴리오-제작-53d": {
    "__comp": "__comp---theme-doc-category-generated-index-page-14-e-640",
    "categoryGeneratedIndex": "categoryGeneratedIndex---docs-category-포트폴리오-제작-08-a-7d1"
  },
  "/docs/category/포트폴리오-평가-프로세스-fb8": {
    "__comp": "__comp---theme-doc-category-generated-index-page-14-e-640",
    "categoryGeneratedIndex": "categoryGeneratedIndex---docs-category-포트폴리오-평가-프로세스b-89-0ff"
  },
  "/docs/category/포트폴리오의-요소-259": {
    "__comp": "__comp---theme-doc-category-generated-index-page-14-e-640",
    "categoryGeneratedIndex": "categoryGeneratedIndex---docs-category-포트폴리오의-요소-1-bf-445"
  },
  "/docs/category/폼-에디터-1e6": {
    "__comp": "__comp---theme-doc-category-generated-index-page-14-e-640",
    "categoryGeneratedIndex": "categoryGeneratedIndex---docs-category-폼-에디터cf-9-678"
  },
  "/docs/category/폼-제작-b69": {
    "__comp": "__comp---theme-doc-category-generated-index-page-14-e-640",
    "categoryGeneratedIndex": "categoryGeneratedIndex---docs-category-폼-제작-940-7e9"
  },
  "/docs/category/하는-방법-de4": {
    "__comp": "__comp---theme-doc-category-generated-index-page-14-e-640",
    "categoryGeneratedIndex": "categoryGeneratedIndex---docs-category-하는-방법fee-2cc"
  },
  "/docs/category/cp-학습-컨텐츠-제작-156": {
    "__comp": "__comp---theme-doc-category-generated-index-page-14-e-640",
    "categoryGeneratedIndex": "categoryGeneratedIndex---docs-category-cp-학습-컨텐츠-제작-24-b-491"
  },
  "/docs/course-operation/using-additional-course-features-3cc": {
    "__comp": "__comp---theme-doc-item-178-a40",
    "content": "content---docs-course-operation-using-additional-course-featuresa-4-b-7c6"
  },
  "/docs/course-operation/using-course-tools/assessment-tool/assessing-tasks-and-group-tasks-310": {
    "__comp": "__comp---theme-doc-item-178-a40",
    "content": "content---docs-course-operation-using-course-tools-assessment-tool-assessing-tasks-and-group-tasks-891-c1e"
  },
  "/docs/course-operation/using-course-tools/assessment-tool/assessing-tests-144": {
    "__comp": "__comp---theme-doc-item-178-a40",
    "content": "content---docs-course-operation-using-course-tools-assessment-tool-assessing-tests-783-b1a"
  },
  "/docs/course-operation/using-course-tools/assessment-tool/assessment-of-course-modules-777": {
    "__comp": "__comp---theme-doc-item-178-a40",
    "content": "content---docs-course-operation-using-course-tools-assessment-tool-assessment-of-course-modulesf-23-171"
  },
  "/docs/course-operation/using-course-tools/assessment-tool/assessment-of-learners-d5e": {
    "__comp": "__comp---theme-doc-item-178-a40",
    "content": "content---docs-course-operation-using-course-tools-assessment-tool-assessment-of-learners-178-a97"
  },
  "/docs/course-operation/using-course-tools/assessment-tool/grading-evaluation-scale-904": {
    "__comp": "__comp---theme-doc-item-178-a40",
    "content": "content---docs-course-operation-using-course-tools-assessment-tool-grading-evaluation-scalef-64-8a3"
  },
  "/docs/course-operation/using-course-tools/assessment-tool/overview-5a1": {
    "__comp": "__comp---theme-doc-item-178-a40",
    "content": "content---docs-course-operation-using-course-tools-assessment-tool-overview-83-e-d48"
  },
  "/docs/course-operation/using-course-tools/assessment-tool/tab-users-693": {
    "__comp": "__comp---theme-doc-item-178-a40",
    "content": "content---docs-course-operation-using-course-tools-assessment-tool-tab-users-8-e-9-ddd"
  },
  "/docs/course-operation/using-course-tools/assessment-tool/the-assessment-form-733": {
    "__comp": "__comp---theme-doc-item-178-a40",
    "content": "content---docs-course-operation-using-course-tools-assessment-tool-the-assessment-form-9-ad-f73"
  },
  "/docs/course-operation/using-course-tools/course-reminders-0fd": {
    "__comp": "__comp---theme-doc-item-178-a40",
    "content": "content---docs-course-operation-using-course-tools-course-reminders-5-e-4-842"
  },
  "/docs/course-operation/using-course-tools/data-archiving-106": {
    "__comp": "__comp---theme-doc-item-178-a40",
    "content": "content---docs-course-operation-using-course-tools-data-archiving-59-a-18c"
  },
  "/docs/course-operation/using-course-tools/lecture-and-absences/lectures-teacher-bcb": {
    "__comp": "__comp---theme-doc-item-178-a40",
    "content": "content---docs-course-operation-using-course-tools-lecture-and-absences-lectures-teachercc-1-8cd"
  },
  "/docs/course-operation/using-course-tools/lecture-and-absences/lectures-user-168": {
    "__comp": "__comp---theme-doc-item-178-a40",
    "content": "content---docs-course-operation-using-course-tools-lecture-and-absences-lectures-userc-6-c-74d"
  },
  "/docs/course-operation/using-course-tools/lecture-and-absences/overview-37e": {
    "__comp": "__comp---theme-doc-item-178-a40",
    "content": "content---docs-course-operation-using-course-tools-lecture-and-absences-overviewcc-8-9dc"
  },
  "/docs/course-operation/using-course-tools/member-management-61a": {
    "__comp": "__comp---theme-doc-item-178-a40",
    "content": "content---docs-course-operation-using-course-tools-member-management-24-d-2dc"
  },
  "/docs/course-operation/using-course-tools/overview-ea8": {
    "__comp": "__comp---theme-doc-item-178-a40",
    "content": "content---docs-course-operation-using-course-tools-overview-5-c-8-f65"
  },
  "/docs/course-operation/using-course-tools/record-of-course-activities-162": {
    "__comp": "__comp---theme-doc-item-178-a40",
    "content": "content---docs-course-operation-using-course-tools-record-of-course-activitiesb-01-433"
  },
  "/docs/course-operation/using-course-tools/storage-folder-05b": {
    "__comp": "__comp---theme-doc-item-178-a40",
    "content": "content---docs-course-operation-using-course-tools-storage-folder-598-cff"
  },
  "/docs/courses-and-catalog/finding-courses-0ad": {
    "__comp": "__comp---theme-doc-item-178-a40",
    "content": "content---docs-courses-and-catalog-finding-coursesd-9-b-033"
  },
  "/docs/courses-and-catalog/info-page-bf3": {
    "__comp": "__comp---theme-doc-item-178-a40",
    "content": "content---docs-courses-and-catalog-info-page-142-f6b"
  },
  "/docs/creating-blogs/blog-ce0": {
    "__comp": "__comp---theme-doc-item-178-a40",
    "content": "content---docs-creating-blogs-blog-49-e-268"
  },
  "/docs/creating-blogs/fourr-stpes-to-your-blog-1f6": {
    "__comp": "__comp---theme-doc-item-178-a40",
    "content": "content---docs-creating-blogs-fourr-stpes-to-your-blog-144-09b"
  },
  "/docs/creating-courses/access-configuration-f88": {
    "__comp": "__comp---theme-doc-item-178-a40",
    "content": "content---docs-creating-courses-access-configuration-46-d-a2c"
  },
  "/docs/creating-courses/course-of-study/-616": {
    "__comp": "__comp---theme-doc-item-178-a40",
    "content": "content---docs-creating-courses-course-of-study-58-a-ae5"
  },
  "/docs/creating-courses/course-of-study/courses-of-study-cda": {
    "__comp": "__comp---theme-doc-item-178-a40",
    "content": "content---docs-creating-courses-course-of-study-courses-of-study-8-d-6-4b2"
  },
  "/docs/creating-courses/course-of-study/creating-learning-path-courses-f6c": {
    "__comp": "__comp---theme-doc-item-178-a40",
    "content": "content---docs-creating-courses-course-of-study-creating-learning-path-courses-323-37e"
  },
  "/docs/creating-courses/course-of-study/overview-b6f": {
    "__comp": "__comp---theme-doc-item-178-a40",
    "content": "content---docs-creating-courses-course-of-study-overview-96-f-006"
  },
  "/docs/creating-courses/course-settings/design-possibilities-of-courses-0ea": {
    "__comp": "__comp---theme-doc-item-178-a40",
    "content": "content---docs-creating-courses-course-settings-design-possibilities-of-courses-59-f-308"
  },
  "/docs/creating-courses/course-settings/lti-access-8c4": {
    "__comp": "__comp---theme-doc-item-178-a40",
    "content": "content---docs-creating-courses-course-settings-lti-access-871-4a3"
  },
  "/docs/creating-courses/course-settings/overview-de4": {
    "__comp": "__comp---theme-doc-item-178-a40",
    "content": "content---docs-creating-courses-course-settings-overview-951-86b"
  },
  "/docs/creating-courses/general-configuration/access-restrictions-cfb": {
    "__comp": "__comp---theme-doc-item-178-a40",
    "content": "content---docs-creating-courses-general-configuration-access-restrictions-357-76b"
  },
  "/docs/creating-courses/general-configuration/deleting-moving-and-copying-course-elements-cdb": {
    "__comp": "__comp---theme-doc-item-178-a40",
    "content": "content---docs-creating-courses-general-configuration-deleting-moving-and-copying-course-elements-54-b-c2c"
  },
  "/docs/creating-courses/general-configuration/overview-c43": {
    "__comp": "__comp---theme-doc-item-178-a40",
    "content": "content---docs-creating-courses-general-configuration-overviewef-2-9ea"
  },
  "/docs/creating-courses/general-information-263": {
    "__comp": "__comp---theme-doc-item-178-a40",
    "content": "content---docs-creating-courses-general-informationb-41-3f9"
  },
  "/docs/creating-courses/in-five-steps-to-your-course-with-the-course-editor-56e": {
    "__comp": "__comp---theme-doc-item-178-a40",
    "content": "content---docs-creating-courses-in-five-steps-to-your-course-with-the-course-editorf-07-f01"
  },
  "/docs/creating-courses/just-a-few-clicks-and-the-course-wizard-3a6": {
    "__comp": "__comp---theme-doc-item-178-a40",
    "content": "content---docs-creating-courses-just-a-few-clicks-and-the-course-wizard-8-d-4-1b2"
  },
  "/docs/creating-courses/using-additional-course-editor-tools-e8b": {
    "__comp": "__comp---theme-doc-item-178-a40",
    "content": "content---docs-creating-courses-using-additional-course-editor-tools-944-9af"
  },
  "/docs/creating-cp-learning-content/cp-editor-c01": {
    "__comp": "__comp---theme-doc-item-178-a40",
    "content": "content---docs-creating-cp-learning-content-cp-editora-3-e-8ae"
  },
  "/docs/creating-cp-learning-content/in-five-steps-to-your-content-package-6b8": {
    "__comp": "__comp---theme-doc-item-178-a40",
    "content": "content---docs-creating-cp-learning-content-in-five-steps-to-your-content-package-716-8d8"
  },
  "/docs/creating-forms/form-editor/overview-155": {
    "__comp": "__comp---theme-doc-item-178-a40",
    "content": "content---docs-creating-forms-form-editor-overview-9-eb-89d"
  },
  "/docs/creating-forms/form-editor/question-rules-174": {
    "__comp": "__comp---theme-doc-item-178-a40",
    "content": "content---docs-creating-forms-form-editor-question-rules-3-e-5-134"
  },
  "/docs/creating-forms/form-editor/rubric-5c9": {
    "__comp": "__comp---theme-doc-item-178-a40",
    "content": "content---docs-creating-forms-form-editor-rubric-7-da-f94"
  },
  "/docs/creating-forms/forms-in-courses/ePortfolio-template-03c": {
    "__comp": "__comp---theme-doc-item-178-a40",
    "content": "content---docs-creating-forms-forms-in-courses-e-portfolio-template-9-cb-f6f"
  },
  "/docs/creating-forms/forms-in-courses/forms-element-727": {
    "__comp": "__comp---theme-doc-item-178-a40",
    "content": "content---docs-creating-forms-forms-in-courses-forms-element-177-ff4"
  },
  "/docs/creating-forms/forms-in-courses/overview-650": {
    "__comp": "__comp---theme-doc-item-178-a40",
    "content": "content---docs-creating-forms-forms-in-courses-overviewcd-5-823"
  },
  "/docs/creating-forms/forms-in-courses/questionnaires-d00": {
    "__comp": "__comp---theme-doc-item-178-a40",
    "content": "content---docs-creating-forms-forms-in-courses-questionnaires-6-e-2-d93"
  },
  "/docs/creating-forms/forms-in-courses/rubric-scoring-f8c": {
    "__comp": "__comp---theme-doc-item-178-a40",
    "content": "content---docs-creating-forms-forms-in-courses-rubric-scoring-9-f-0-a33"
  },
  "/docs/creating-forms/general-information-fc9": {
    "__comp": "__comp---theme-doc-item-178-a40",
    "content": "content---docs-creating-forms-general-informationbb-9-97b"
  },
  "/docs/creating-forms/three-steps-to-your-form-e34": {
    "__comp": "__comp---theme-doc-item-178-a40",
    "content": "content---docs-creating-forms-three-steps-to-your-formdf-8-60b"
  },
  "/docs/creating-podcasts/four-steps-to-your-podcast-c99": {
    "__comp": "__comp---theme-doc-item-178-a40",
    "content": "content---docs-creating-podcasts-four-steps-to-your-podcastf-8-d-ba4"
  },
  "/docs/creating-podcasts/podcast-e41": {
    "__comp": "__comp---theme-doc-item-178-a40",
    "content": "content---docs-creating-podcasts-podcast-9-f-8-c26"
  },
  "/docs/creating-portfolios/competences-tags-d0f": {
    "__comp": "__comp---theme-doc-item-178-a40",
    "content": "content---docs-creating-portfolios-competences-tags-5-a-4-3bd"
  },
  "/docs/creating-portfolios/componenets-of-the-portfolio/media-center-834": {
    "__comp": "__comp---theme-doc-item-178-a40",
    "content": "content---docs-creating-portfolios-componenets-of-the-portfolio-media-center-72-c-d67"
  },
  "/docs/creating-portfolios/componenets-of-the-portfolio/my-entries-e5e": {
    "__comp": "__comp---theme-doc-item-178-a40",
    "content": "content---docs-creating-portfolios-componenets-of-the-portfolio-my-entriesba-0-537"
  },
  "/docs/creating-portfolios/componenets-of-the-portfolio/my-portfolio-binders-09b": {
    "__comp": "__comp---theme-doc-item-178-a40",
    "content": "content---docs-creating-portfolios-componenets-of-the-portfolio-my-portfolio-bindersf-60-81f"
  },
  "/docs/creating-portfolios/componenets-of-the-portfolio/overview-493": {
    "__comp": "__comp---theme-doc-item-178-a40",
    "content": "content---docs-creating-portfolios-componenets-of-the-portfolio-overview-1-de-39e"
  },
  "/docs/creating-portfolios/componenets-of-the-portfolio/shared-by-me-c73": {
    "__comp": "__comp---theme-doc-item-178-a40",
    "content": "content---docs-creating-portfolios-componenets-of-the-portfolio-shared-by-mede-0-3b2"
  },
  "/docs/creating-portfolios/componenets-of-the-portfolio/shared-with-me-e71": {
    "__comp": "__comp---theme-doc-item-178-a40",
    "content": "content---docs-creating-portfolios-componenets-of-the-portfolio-shared-with-meab-6-987"
  },
  "/docs/creating-portfolios/general-information-1b6": {
    "__comp": "__comp---theme-doc-item-178-a40",
    "content": "content---docs-creating-portfolios-general-informationd-0-a-c94"
  },
  "/docs/creating-portfolios/multiple-use-of-entries-71e": {
    "__comp": "__comp---theme-doc-item-178-a40",
    "content": "content---docs-creating-portfolios-multiple-use-of-entries-9-ce-d9a"
  },
  "/docs/creating-portfolios/process-of-an-assessment-portfolio/creating-portfolio-tasks-44b": {
    "__comp": "__comp---theme-doc-item-178-a40",
    "content": "content---docs-creating-portfolios-process-of-an-assessment-portfolio-creating-portfolio-taskscc-2-028"
  },
  "/docs/creating-portfolios/process-of-an-assessment-portfolio/overview-152": {
    "__comp": "__comp---theme-doc-item-178-a40",
    "content": "content---docs-creating-portfolios-process-of-an-assessment-portfolio-overview-788-ea9"
  },
  "/docs/creating-portfolios/process-of-an-assessment-portfolio/portfolio-assignment-grading-062": {
    "__comp": "__comp---theme-doc-item-178-a40",
    "content": "content---docs-creating-portfolios-process-of-an-assessment-portfolio-portfolio-assignment-grading-893-8d4"
  },
  "/docs/creating-portfolios/process-of-an-assessment-portfolio/portfolio-task-de4": {
    "__comp": "__comp---theme-doc-item-178-a40",
    "content": "content---docs-creating-portfolios-process-of-an-assessment-portfolio-portfolio-task-3-c-9-385"
  },
  "/docs/creating-portfolios/process-of-an-assessment-portfolio/template-administration-aba": {
    "__comp": "__comp---theme-doc-item-178-a40",
    "content": "content---docs-creating-portfolios-process-of-an-assessment-portfolio-template-administration-771-a25"
  },
  "/docs/creating-portfolios/process-of-an-assessment-portfolio/template-creation-309": {
    "__comp": "__comp---theme-doc-item-178-a40",
    "content": "content---docs-creating-portfolios-process-of-an-assessment-portfolio-template-creation-46-b-97c"
  },
  "/docs/creating-portfolios/the-portfolio-editor-a48": {
    "__comp": "__comp---theme-doc-item-178-a40",
    "content": "content---docs-creating-portfolios-the-portfolio-editorea-0-638"
  },
  "/docs/creating-portfolios/three-steps-to-your-portfolio-binder-d04": {
    "__comp": "__comp---theme-doc-item-178-a40",
    "content": "content---docs-creating-portfolios-three-steps-to-your-portfolio-binder-54-e-c9c"
  },
  "/docs/creating-tasks/assess-tasks-bf7": {
    "__comp": "__comp---theme-doc-item-178-a40",
    "content": "content---docs-creating-tasks-assess-tasksb-3-c-856"
  },
  "/docs/creating-tasks/task-further-configuration-b0d": {
    "__comp": "__comp---theme-doc-item-178-a40",
    "content": "content---docs-creating-tasks-task-further-configurationcd-8-bcf"
  },
  "/docs/creating-tasks/three-steps-to-your-task-161": {
    "__comp": "__comp---theme-doc-item-178-a40",
    "content": "content---docs-creating-tasks-three-steps-to-your-taskf-2-e-e3d"
  },
  "/docs/creating-tests/changing-from-version-b36": {
    "__comp": "__comp---theme-doc-item-178-a40",
    "content": "content---docs-creating-tests-changing-from-versionbe-7-957"
  },
  "/docs/creating-tests/four-steps-to-your-test-e67": {
    "__comp": "__comp---theme-doc-item-178-a40",
    "content": "content---docs-creating-tests-four-steps-to-your-test-67-d-e63"
  },
  "/docs/creating-tests/general-information-f4f": {
    "__comp": "__comp---theme-doc-item-178-a40",
    "content": "content---docs-creating-tests-general-information-82-d-ae1"
  },
  "/docs/creating-tests/qti-2.1/configure-tests-cc6": {
    "__comp": "__comp---theme-doc-item-178-a40",
    "content": "content---docs-creating-tests-qti-2-1-configure-testsb-40-bc3"
  },
  "/docs/creating-tests/qti-2.1/confiture-test-questions-f99": {
    "__comp": "__comp---theme-doc-item-178-a40",
    "content": "content---docs-creating-tests-qti-2-1-confiture-test-questions-2-e-2-c61"
  },
  "/docs/creating-tests/qti-2.1/overview-5bd": {
    "__comp": "__comp---theme-doc-item-178-a40",
    "content": "content---docs-creating-tests-qti-2-1-overview-2-ba-6c7"
  },
  "/docs/creating-tests/qti-2.1/test-question-types-6cf": {
    "__comp": "__comp---theme-doc-item-178-a40",
    "content": "content---docs-creating-tests-qti-2-1-test-question-types-491-a35"
  },
  "/docs/creating-tests/test-settings-e67": {
    "__comp": "__comp---theme-doc-item-178-a40",
    "content": "content---docs-creating-tests-test-settings-50-b-b25"
  },
  "/docs/creating-tests/tests-at-course-level-ccb": {
    "__comp": "__comp---theme-doc-item-178-a40",
    "content": "content---docs-creating-tests-tests-at-course-levela-13-c6c"
  },
  "/docs/creating-videos/course-element-video-0aa": {
    "__comp": "__comp---theme-doc-item-178-a40",
    "content": "content---docs-creating-videos-course-element-videoe-33-f97"
  },
  "/docs/creating-videos/learning-resource-video-98c": {
    "__comp": "__comp---theme-doc-item-178-a40",
    "content": "content---docs-creating-videos-learning-resource-video-257-c2d"
  },
  "/docs/creating-videos/single-page-add-edit-video-a5f": {
    "__comp": "__comp---theme-doc-item-178-a40",
    "content": "content---docs-creating-videos-single-page-add-edit-videoc-25-155"
  },
  "/docs/creating-videos/video-upload-3c8": {
    "__comp": "__comp---theme-doc-item-178-a40",
    "content": "content---docs-creating-videos-video-uploadc-45-0f9"
  },
  "/docs/creating-wikis/four-steps-to-your-wiki-5e3": {
    "__comp": "__comp---theme-doc-item-178-a40",
    "content": "content---docs-creating-wikis-four-steps-to-your-wikiebb-6af"
  },
  "/docs/curriculum-management/curriculum-management-5ea": {
    "__comp": "__comp---theme-doc-item-178-a40",
    "content": "content---docs-curriculum-management-curriculum-management-84-f-a39"
  },
  "/docs/e-assessment/assessment-mode-10e": {
    "__comp": "__comp---theme-doc-item-178-a40",
    "content": "content---docs-e-assessment-assessment-mode-0-f-2-ca0"
  },
  "/docs/e-assessment/coaching-0d1": {
    "__comp": "__comp---theme-doc-item-178-a40",
    "content": "content---docs-e-assessment-coachingc-12-58a"
  },
  "/docs/e-assessment/performance-assessment-eb3": {
    "__comp": "__comp---theme-doc-item-178-a40",
    "content": "content---docs-e-assessment-performance-assessment-210-6b0"
  },
  "/docs/group/create-groups-dd2": {
    "__comp": "__comp---theme-doc-item-178-a40",
    "content": "content---docs-group-create-groupsabf-871"
  },
  "/docs/group/group-administration-c1d": {
    "__comp": "__comp---theme-doc-item-178-a40",
    "content": "content---docs-group-group-administrationa-69-8be"
  },
  "/docs/group/group-management-37e": {
    "__comp": "__comp---theme-doc-item-178-a40",
    "content": "content---docs-group-group-management-23-c-f5a"
  },
  "/docs/group/lti-access-182": {
    "__comp": "__comp---theme-doc-item-178-a40",
    "content": "content---docs-group-lti-accessd-22-978"
  },
  "/docs/group/using-group-tools-b4e": {
    "__comp": "__comp---theme-doc-item-178-a40",
    "content": "content---docs-group-using-group-toolsbcf-2f8"
  },
  "/docs/how-to/create-a-bulk-assessment-3ce": {
    "__comp": "__comp---theme-doc-item-178-a40",
    "content": "content---docs-how-to-create-a-bulk-assessment-3-d-6-78e"
  },
  "/docs/how-to/customize-the-course-design-93b": {
    "__comp": "__comp---theme-doc-item-178-a40",
    "content": "content---docs-how-to-customize-the-course-design-2-d-7-e2a"
  },
  "/docs/introduction/about-learnize-7b6": {
    "__comp": "__comp---theme-doc-item-178-a40",
    "content": "content---docs-introduction-about-learnize-15-a-a03"
  },
  "/docs/introduction/coach-317": {
    "__comp": "__comp---theme-doc-item-178-a40",
    "content": "content---docs-introduction-coachf-6-b-dc9"
  },
  "/docs/introduction/guest-access-826": {
    "__comp": "__comp---theme-doc-item-178-a40",
    "content": "content---docs-introduction-guest-access-5-e-0-a65"
  },
  "/docs/introduction/requirements-c19": {
    "__comp": "__comp---theme-doc-item-178-a40",
    "content": "content---docs-introduction-requirementsd-39-317"
  },
  "/docs/introduction/roles-and-rights-68f": {
    "__comp": "__comp---theme-doc-item-178-a40",
    "content": "content---docs-introduction-roles-and-rightsad-7-b51"
  },
  "/docs/introduction/technology-0f3": {
    "__comp": "__comp---theme-doc-item-178-a40",
    "content": "content---docs-introduction-technologyc-59-d03"
  },
  "/docs/learning-activities/additional-course-features-33d": {
    "__comp": "__comp---theme-doc-item-178-a40",
    "content": "content---docs-learning-activities-additional-course-featuresfbe-360"
  },
  "/docs/learning-activities/course-problems-and-error-messages-930": {
    "__comp": "__comp---theme-doc-item-178-a40",
    "content": "content---docs-learning-activities-course-problems-and-error-messages-212-646"
  },
  "/docs/learning-activities/exams-1cf": {
    "__comp": "__comp---theme-doc-item-178-a40",
    "content": "content---docs-learning-activities-examsd-4-f-525"
  },
  "/docs/learning-activities/working-with-course-elements/overview-55e": {
    "__comp": "__comp---theme-doc-item-178-a40",
    "content": "content---docs-learning-activities-working-with-course-elements-overviewcb-3-b5d"
  },
  "/docs/learning-activities/working-with-course-elements/working-with-forums-225": {
    "__comp": "__comp---theme-doc-item-178-a40",
    "content": "content---docs-learning-activities-working-with-course-elements-working-with-forums-403-e58"
  },
  "/docs/learning-activities/working-with-course-elements/working-with-tasks-71e": {
    "__comp": "__comp---theme-doc-item-178-a40",
    "content": "content---docs-learning-activities-working-with-course-elements-working-with-tasks-416-f27"
  },
  "/docs/learning-activities/working-with-course-elements/working-with-tests-889": {
    "__comp": "__comp---theme-doc-item-178-a40",
    "content": "content---docs-learning-activities-working-with-course-elements-working-with-tests-281-906"
  },
  "/docs/learning-activities/working-with-course-elements/working-with-topic-f9c": {
    "__comp": "__comp---theme-doc-item-178-a40",
    "content": "content---docs-learning-activities-working-with-course-elements-working-with-topic-299-30e"
  },
  "/docs/learning-activities/working-with-course-elements/working-with-wiki-1b3": {
    "__comp": "__comp---theme-doc-item-178-a40",
    "content": "content---docs-learning-activities-working-with-course-elements-working-with-wiki-89-b-ce3"
  },
  "/docs/managing-topics/three-step-to-create-and-manage-topics-b40": {
    "__comp": "__comp---theme-doc-item-178-a40",
    "content": "content---docs-managing-topics-three-step-to-create-and-manage-topics-866-3df"
  },
  "/docs/personal/chat-189": {
    "__comp": "__comp---theme-doc-item-178-a40",
    "content": "content---docs-personal-chat-1-af-0ed"
  },
  "/docs/personal/configuration/covid-certificate-b55": {
    "__comp": "__comp---theme-doc-item-178-a40",
    "content": "content---docs-personal-configuration-covid-certificatea-3-f-60e"
  },
  "/docs/personal/configuration/overview-dc7": {
    "__comp": "__comp---theme-doc-item-178-a40",
    "content": "content---docs-personal-configuration-overviewd-78-978"
  },
  "/docs/personal/full-text-search-e96": {
    "__comp": "__comp---theme-doc-item-178-a40",
    "content": "content---docs-personal-full-text-search-57-b-8fe"
  },
  "/docs/personal/math-formula-ed5": {
    "__comp": "__comp---theme-doc-item-178-a40",
    "content": "content---docs-personal-math-formula-398-2bc"
  },
  "/docs/personal/personal-menu/calendar-cf3": {
    "__comp": "__comp---theme-doc-item-178-a40",
    "content": "content---docs-personal-personal-menu-calendaraa-5-617"
  },
  "/docs/personal/personal-menu/email-191": {
    "__comp": "__comp---theme-doc-item-178-a40",
    "content": "content---docs-personal-personal-menu-email-329-01f"
  },
  "/docs/personal/personal-menu/overview-783": {
    "__comp": "__comp---theme-doc-item-178-a40",
    "content": "content---docs-personal-personal-menu-overview-770-2e5"
  },
  "/docs/personal/personal-menu/personal-folders-466": {
    "__comp": "__comp---theme-doc-item-178-a40",
    "content": "content---docs-personal-personal-menu-personal-folders-231-d6a"
  },
  "/docs/personal/portal-configuration-0f5": {
    "__comp": "__comp---theme-doc-item-178-a40",
    "content": "content---docs-personal-portal-configuration-57-b-2d9"
  },
  "/docs/personal/working with tables-005": {
    "__comp": "__comp---theme-doc-item-178-a40",
    "content": "content---docs-personal-working-with-tables-72-a-14a"
  },
  "/docs/question-bank/administration-9bc": {
    "__comp": "__comp---theme-doc-item-178-a40",
    "content": "content---docs-question-bank-administration-05-f-b64"
  },
  "/docs/question-bank/data-management-9a2": {
    "__comp": "__comp---theme-doc-item-178-a40",
    "content": "content---docs-question-bank-data-managementff-7-450"
  },
  "/docs/question-bank/item-detailed-view-40f": {
    "__comp": "__comp---theme-doc-item-178-a40",
    "content": "content---docs-question-bank-item-detailed-view-74-c-237"
  },
  "/docs/question-bank/possible-operations-60b": {
    "__comp": "__comp---theme-doc-item-178-a40",
    "content": "content---docs-question-bank-possible-operations-574-bc0"
  },
  "/docs/question-bank/review-process-4f1": {
    "__comp": "__comp---theme-doc-item-178-a40",
    "content": "content---docs-question-bank-review-process-908-452"
  },
  "/docs/question-bank/search-eab": {
    "__comp": "__comp---theme-doc-item-178-a40",
    "content": "content---docs-question-bank-search-94-b-16a"
  },
  "/docs/question-bank/sharing-options-7a9": {
    "__comp": "__comp---theme-doc-item-178-a40",
    "content": "content---docs-question-bank-sharing-optionscd-0-b7c"
  },
  "/docs/registration/login-page-eb4": {
    "__comp": "__comp---theme-doc-item-178-a40",
    "content": "content---docs-registration-login-pagee-1-e-44e"
  },
  "/docs/registration/logout-2de": {
    "__comp": "__comp---theme-doc-item-178-a40",
    "content": "content---docs-registration-logout-7-f-7-909"
  },
  "/docs/supported-technologies/using-webdav-11a": {
    "__comp": "__comp---theme-doc-item-178-a40",
    "content": "content---docs-supported-technologies-using-webdava-56-460"
  },
  "/docs/types-of-course-element/assessment/course-element-assessment-710": {
    "__comp": "__comp---theme-doc-item-178-a40",
    "content": "content---docs-types-of-course-element-assessment-course-element-assessment-6-b-4-ddc"
  },
  "/docs/types-of-course-element/assessment/course-element-checklist-4b3": {
    "__comp": "__comp---theme-doc-item-178-a40",
    "content": "content---docs-types-of-course-element-assessment-course-element-checkliste-1-e-c9f"
  },
  "/docs/types-of-course-element/assessment/overview-3bc": {
    "__comp": "__comp---theme-doc-item-178-a40",
    "content": "content---docs-types-of-course-element-assessment-overview-0-fa-48f"
  },
  "/docs/types-of-course-element/communication-and-organisation/bbb-frequently-asked-question-51a": {
    "__comp": "__comp---theme-doc-item-178-a40",
    "content": "content---docs-types-of-course-element-communication-and-organisation-bbb-frequently-asked-questionca-1-d52"
  },
  "/docs/types-of-course-element/communication-and-organisation/course-element-adobe-connect-9f6": {
    "__comp": "__comp---theme-doc-item-178-a40",
    "content": "content---docs-types-of-course-element-communication-and-organisation-course-element-adobe-connecta-50-01b"
  },
  "/docs/types-of-course-element/communication-and-organisation/course-element-bigbluebutton-0d2": {
    "__comp": "__comp---theme-doc-item-178-a40",
    "content": "content---docs-types-of-course-element-communication-and-organisation-course-element-bigbluebutton-9-b-2-32a"
  },
  "/docs/types-of-course-element/communication-and-organisation/course-element-gotomeetings-294": {
    "__comp": "__comp---theme-doc-item-178-a40",
    "content": "content---docs-types-of-course-element-communication-and-organisation-course-element-gotomeetingsc-8-a-2c6"
  },
  "/docs/types-of-course-element/communication-and-organisation/course-element-microsoft-teams-aa5": {
    "__comp": "__comp---theme-doc-item-178-a40",
    "content": "content---docs-types-of-course-element-communication-and-organisation-course-element-microsoft-teams-362-486"
  },
  "/docs/types-of-course-element/communication-and-organisation/course-element-opennmettings-29f": {
    "__comp": "__comp---theme-doc-item-178-a40",
    "content": "content---docs-types-of-course-element-communication-and-organisation-course-element-opennmettingsee-7-0d2"
  },
  "/docs/types-of-course-element/communication-and-organisation/course-element-vitero-288": {
    "__comp": "__comp---theme-doc-item-178-a40",
    "content": "content---docs-types-of-course-element-communication-and-organisation-course-element-vitero-3-f-5-609"
  },
  "/docs/types-of-course-element/communication-and-organisation/overview-fd4": {
    "__comp": "__comp---theme-doc-item-178-a40",
    "content": "content---docs-types-of-course-element-communication-and-organisation-overview-007-79f"
  },
  "/docs/types-of-course-element/communication-and-organisation/virtual-classrooms-a88": {
    "__comp": "__comp---theme-doc-item-178-a40",
    "content": "content---docs-types-of-course-element-communication-and-organisation-virtual-classroomsaba-7c6"
  },
  "/docs/types-of-course-element/course_element4-69c": {
    "__comp": "__comp---theme-doc-item-178-a40",
    "content": "content---docs-types-of-course-element-course-element-4-c-81-cb6"
  },
  "/docs/types-of-course-element/course_element5-595": {
    "__comp": "__comp---theme-doc-item-178-a40",
    "content": "content---docs-types-of-course-element-course-element-5-bb-1-418"
  },
  "/docs/types-of-course-element/knowledge-transfer/course-element-card2brain-c7a": {
    "__comp": "__comp---theme-doc-item-178-a40",
    "content": "content---docs-types-of-course-element-knowledge-transfer-course-element-card-2-brain-832-5e1"
  },
  "/docs/types-of-course-element/knowledge-transfer/course-element-folder-11e": {
    "__comp": "__comp---theme-doc-item-178-a40",
    "content": "content---docs-types-of-course-element-knowledge-transfer-course-element-folder-71-b-9a6"
  },
  "/docs/types-of-course-element/knowledge-transfer/course-element-mediasite-c19": {
    "__comp": "__comp---theme-doc-item-178-a40",
    "content": "content---docs-types-of-course-element-knowledge-transfer-course-element-mediasited-6-b-109"
  },
  "/docs/types-of-course-element/knowledge-transfer/course-element-scorn-5dd": {
    "__comp": "__comp---theme-doc-item-178-a40",
    "content": "content---docs-types-of-course-element-knowledge-transfer-course-element-scorn-831-638"
  },
  "/docs/types-of-course-element/knowledge-transfer/course-element-single-page-c0d": {
    "__comp": "__comp---theme-doc-item-178-a40",
    "content": "content---docs-types-of-course-element-knowledge-transfer-course-element-single-pageca-3-a13"
  },
  "/docs/types-of-course-element/knowledge-transfer/course-element-structure-4db": {
    "__comp": "__comp---theme-doc-item-178-a40",
    "content": "content---docs-types-of-course-element-knowledge-transfer-course-element-structure-995-c48"
  },
  "/docs/types-of-course-element/knowledge-transfer/overview-3d5": {
    "__comp": "__comp---theme-doc-item-178-a40",
    "content": "content---docs-types-of-course-element-knowledge-transfer-overview-855-640"
  },
  "/-f56": {
    "__comp": "__comp---site-src-pages-index-jsc-4-f-f99",
    "__context": {
      "plugin": "plugin---markdown-pageb-09-bff"
    },
    "config": "config---5-e-9-4f3"
  }
}